parallel/__init__.py
parallel/errors.py
parallel/exceptions.py
parallel/models.py
parallel/process.py
parallel/utils.py
python_parallel-0.9.0.dist-info/LICENSE
python_parallel-0.9.0.dist-info/WHEEL
python_parallel-0.9.0.dist-info/METADATA
python_parallel-0.9.0.dist-info/RECORD
